suiutils_py/__init__.py
suiutils_py/models.py
suiutils_py/provider.py
suiutils_py/rpc_tx_data_serializer.py
suiutils_py/signer.py
suiutils_py/signer_with_provider.py
suiutils_py/wallet.py
suiutils_py-1.1.0.dist-info/METADATA
suiutils_py-1.1.0.dist-info/WHEEL
suiutils_py-1.1.0.dist-info/top_level.txt
suiutils_py-1.1.0.dist-info/RECORD
