Metadata-Version: 2.1
Name: suiutils-py
Version: 1.1.0
Home-page: https://github.com/satisfywithmylife/sui_python_sdk
Author: shawngmy, yanjlee
Author-email: shawngmy@gmail.com, yanjlee@163.com
Classifier: Programming Language :: Python :: 3
Classifier: License :: OSI Approved :: MIT License
Classifier: Operating System :: OS Independent
Requires-Python: >=3.7
Requires-Dist: httpx
Requires-Dist: pynacl
Requires-Dist: inflect
Requires-Dist: pick
Requires-Dist: path
Requires-Dist: GuDory2
Requires-Dist: configparser
Requires-Dist: pypandoc
Requires-Dist: python-slugify
Requires-Dist: vb-console
Requires-Dist: peppercorn
Requires-Dist: node
Requires-Dist: odict
Requires-Dist: certifi
Requires-Dist: charset-normalizer
Requires-Dist: docutils
Requires-Dist: idna
Requires-Dist: importlib-metadata
Requires-Dist: keyring
Requires-Dist: mdurl
Requires-Dist: more-itertools
Requires-Dist: nh3
Requires-Dist: pkginfo
Requires-Dist: plumber
Requires-Dist: pygments
Requires-Dist: requests-toolbelt
Requires-Dist: readme-renderer
Requires-Dist: requests
